readstore_basic/__init__.py
readstore_basic/__version__.py
readstore_basic/readstore_server.py
readstore_basic/readstore_server_config.yaml
readstore_basic/requirements.txt
readstore_basic/backend/__init__.py
readstore_basic/backend/backup.py
readstore_basic/backend/launch_backend.py
readstore_basic/backend/manage.py
readstore_basic/backend/setup_user.py
readstore_basic/backend/app/__init__.py
readstore_basic/backend/app/admin.py
readstore_basic/backend/app/apps.py
readstore_basic/backend/app/authentication.py
readstore_basic/backend/app/ext_views.py
readstore_basic/backend/app/models.py
readstore_basic/backend/app/permissions.py
readstore_basic/backend/app/pipelines.py
readstore_basic/backend/app/serializers.py
readstore_basic/backend/app/views.py
readstore_basic/backend/backend/__init__.py
readstore_basic/backend/backend/asgi.py
readstore_basic/backend/backend/urls.py
readstore_basic/backend/backend/wsgi.py
readstore_basic/backend/settings/__init__.py
readstore_basic/backend/settings/base.py
readstore_basic/backend/settings/development.py
readstore_basic/backend/settings/production.py
readstore_basic/frontend/__init__.py
readstore_basic/frontend/streamlit/__init__.py
readstore_basic/frontend/streamlit/app.py
readstore_basic/frontend/streamlit/datamanager.py
readstore_basic/frontend/streamlit/exceptions.py
readstore_basic/frontend/streamlit/extensions.py
readstore_basic/frontend/streamlit/live.py
readstore_basic/frontend/streamlit/styles.py
readstore_basic/frontend/streamlit/uiconfig.py
readstore_basic/frontend/streamlit/uidataclasses.py
readstore_basic/frontend/streamlit/.streamlit/config.toml
readstore_basic/frontend/streamlit/app_pages/__init__.py
readstore_basic/frontend/streamlit/app_pages/admin.py
readstore_basic/frontend/streamlit/app_pages/dataset.py
readstore_basic/frontend/streamlit/app_pages/login.py
readstore_basic/frontend/streamlit/app_pages/logout.py
readstore_basic/frontend/streamlit/app_pages/project.py
readstore_basic-1.3.6.dist-info/LICENSE
readstore_basic-1.3.6.dist-info/METADATA
readstore_basic-1.3.6.dist-info/NOTICE
readstore_basic-1.3.6.dist-info/WHEEL
readstore_basic-1.3.6.dist-info/entry_points.txt
readstore_basic-1.3.6.dist-info/top_level.txt
readstore_basic-1.3.6.dist-info/RECORD
