Metadata-Version: 2.2
Name: readstore-basic
Version: 1.3.6
Summary: ReadStore Basic Is A Python Package For Managing FASTQ Files and NGS Projects
Home-page: https://github.com/EvobyteDigitalBiology/readstore
Author: Jonathan Alles
Author-email: Jonathan.Alles@evo-byte.com
License: Commercial
Classifier: Programming Language :: Python :: 3
Classifier: License :: Other/Proprietary License
Classifier: Operating System :: OS Independent
Requires-Python: >=3.10
License-File: LICENSE
License-File: NOTICE
Requires-Dist: Django>=5.1.4
Requires-Dist: djangorestframework>=3.15.2
Requires-Dist: djangorestframework_simplejwt>=5.4.0
Requires-Dist: requests>=2.32.3
Requires-Dist: gunicorn>=23.0.0
Requires-Dist: pysam>=0.22.1
Requires-Dist: pyyaml>=6.0.2
Requires-Dist: streamlit>=1.41.0
Requires-Dist: pydantic>=2.10.3
Requires-Dist: pandas>=2.2.3
Requires-Dist: openpyxl>=3.1.5
Dynamic: author
Dynamic: author-email
Dynamic: classifier
Dynamic: description
Dynamic: description-content-type
Dynamic: home-page
Dynamic: license
Dynamic: requires-dist
Dynamic: requires-python
Dynamic: summary
